idx/__init__.py
idx/main.py
idx/tasks/__init__.py
idx/tasks/show.py
idx/tasks/show2.py
bindex-0.0.10.dist-info/METADATA
bindex-0.0.10.dist-info/WHEEL
bindex-0.0.10.dist-info/entry_points.txt
bindex-0.0.10.dist-info/top_level.txt
bindex-0.0.10.dist-info/RECORD
