Metadata-Version: 2.1
Name: bindex
Version: 0.0.10
Summary: Commands for Beni
Author-email: Beni Mang <benimang@126.com>
Maintainer-email: Beni Mang <benimang@126.com>
Keywords: benimang,beni,bindex
Requires-Python: >=3.10
Requires-Dist: aioconsole ==0.6.2
Requires-Dist: aiofiles ==23.2.1
Requires-Dist: aiohttp ==3.8.5
Requires-Dist: aiosignal ==1.3.1
Requires-Dist: annotated-types ==0.5.0
Requires-Dist: async-timeout ==4.0.3
Requires-Dist: attrs ==23.1.0
Requires-Dist: autopep8 ==2.0.4
Requires-Dist: benimang ==0.4.27
Requires-Dist: build ==1.0.3
Requires-Dist: certifi ==2023.7.22
Requires-Dist: charset-normalizer ==3.2.0
Requires-Dist: click ==8.1.7
Requires-Dist: colorama ==0.4.6
Requires-Dist: docutils ==0.20.1
Requires-Dist: frozenlist ==1.4.0
Requires-Dist: greenlet ==2.0.2
Requires-Dist: idna ==3.4
Requires-Dist: importlib-metadata ==6.8.0
Requires-Dist: jaraco.classes ==3.3.0
Requires-Dist: keyring ==24.2.0
Requires-Dist: markdown-it-py ==3.0.0
Requires-Dist: mdurl ==0.1.2
Requires-Dist: more-itertools ==10.1.0
Requires-Dist: multidict ==6.0.4
Requires-Dist: nest-asyncio ==1.5.8
Requires-Dist: nh3 ==0.2.14
Requires-Dist: orjson ==3.9.7
Requires-Dist: packaging ==23.1
Requires-Dist: pkginfo ==1.9.6
Requires-Dist: playwright ==1.37.0
Requires-Dist: portalocker ==2.8.2
Requires-Dist: pretty-errors ==1.2.25
Requires-Dist: prettytable ==3.9.0
Requires-Dist: pycodestyle ==2.11.0
Requires-Dist: pydantic ==2.3.0
Requires-Dist: pydantic-core ==2.6.3
Requires-Dist: pyee ==9.0.4
Requires-Dist: Pygments ==2.16.1
Requires-Dist: pyperclip ==1.8.2
Requires-Dist: pyproject-hooks ==1.0.0
Requires-Dist: pywin32 ==306
Requires-Dist: pywin32-ctypes ==0.2.2
Requires-Dist: PyYAML ==6.0.1
Requires-Dist: qiniu ==7.11.1
Requires-Dist: readme-renderer ==42.0
Requires-Dist: requests ==2.31.0
Requires-Dist: requests-toolbelt ==1.0.0
Requires-Dist: rfc3986 ==2.0.0
Requires-Dist: rich ==13.5.3
Requires-Dist: twine ==4.0.2
Requires-Dist: typer ==0.9.0
Requires-Dist: typing-extensions ==4.8.0
Requires-Dist: tzdata ==2023.3
Requires-Dist: urllib3 ==2.0.4
Requires-Dist: wcwidth ==0.2.6
Requires-Dist: yarl ==1.9.2
Requires-Dist: zipp ==3.16.2
